[
    {
        "name": "id",
        "dbType": "increments",
        "htmlType": null,
        "validations": null,
        "searchable": false,
        "fillable": false,
        "primary": true,
        "inForm": false,
        "inIndex": false,
        "inView": false
    },
    {
        "name": "from",
        "dbType": "integer",
        "htmlType": "select",
        "validations": "required",
        "searchable": true,
        "fillable": true,
        "primary": false,
        "inForm": true,
        "inIndex": true,
        "inView": true
    },
    {
        "name": "to",
        "dbType": "integer",
        "htmlType": "number",
        "validations": "required",
        "searchable": true,
        "fillable": true,
        "primary": false,
        "inForm": true,
        "inIndex": true,
        "inView": true
    },
    {
        "name": "date",
        "dbType": "date",
        "htmlType": "date",
        "validations": "required",
        "searchable": true,
        "fillable": true,
        "primary": false,
        "inForm": true,
        "inIndex": true,
        "inView": true
    },
    {
        "name": "time",
        "dbType": "time",
        "htmlType": "text",
        "validations": "",
        "searchable": true,
        "fillable": true,
        "primary": false,
        "inForm": true,
        "inIndex": true,
        "inView": true
    },
    {
        "name": "flight",
        "dbType": "string,10",
        "htmlType": "text",
        "validations": "",
        "searchable": true,
        "fillable": true,
        "primary": false,
        "inForm": true,
        "inIndex": true,
        "inView": true
    },
    {
        "name": "type",
        "dbType": "tinyinteger",
        "htmlType": "select,STANDART,VIP,GROUP",
        "validations": "",
        "searchable": true,
        "fillable": true,
        "primary": false,
        "inForm": true,
        "inIndex": true,
        "inView": true
    },
    {
        "name": "customer_id",
        "dbType": "smallinteger",
        "htmlType": "select",
        "validations": "",
        "searchable": true,
        "fillable": true,
        "primary": false,
        "inForm": true,
        "inIndex": true,
        "inView": true
    },
    {
        "name": "info",
        "dbType": "string,100",
        "htmlType": "text",
        "validations": "",
        "searchable": true,
        "fillable": true,
        "primary": false,
        "inForm": true,
        "inIndex": true,
        "inView": true
    },
    {
        "name": "created_at",
        "dbType": "timestamp",
        "htmlType": null,
        "validations": null,
        "searchable": false,
        "fillable": false,
        "primary": false,
        "inForm": false,
        "inIndex": false,
        "inView": true
    },
    {
        "name": "updated_at",
        "dbType": "timestamp",
        "htmlType": null,
        "validations": null,
        "searchable": false,
        "fillable": false,
        "primary": false,
        "inForm": false,
        "inIndex": false,
        "inView": true
    },
    {
        "type": "relation",
        "relation": "1t1,"
    },
    {
        "type": "relation",
        "relation": "1t1,"
    },
    {
        "type": "relation",
        "relation": "1t1 Customer,"
    }
]